rftk/cloud_functions/__init__.py
rftk/cloud_functions/services/__init__.py
rftk/cloud_functions/services/classes.py
rftk/cloud_functions/services/clearbit_service.py
rftk/cloud_functions/services/constants.py
rftk/cloud_functions/services/crawler_service.py
rftk/cloud_functions/services/deployment.py
rftk/cloud_functions/services/email_provider.py
rftk/cloud_functions/services/email_provider_lookup_service.py
rftk/cloud_functions/services/functions.py
rftk/cloud_functions/services/mobile_friendly_service.py
rftk/cloud_functions/services/schemas.py
rftk/cloud_functions/services/wordpress.py
rftk/cloud_functions/services/wordpress_lookup_service.py
the_refinery_toolkit-0.6.55.dist-info/LICENSE
the_refinery_toolkit-0.6.55.dist-info/METADATA
the_refinery_toolkit-0.6.55.dist-info/WHEEL
the_refinery_toolkit-0.6.55.dist-info/top_level.txt
the_refinery_toolkit-0.6.55.dist-info/RECORD
